trojai/__init__.py
trojai/datagen/__init__.py
trojai/datagen/albumentations_xforms.py
trojai/datagen/blend_merges.py
trojai/datagen/common_label_behaviors.py
trojai/datagen/common_text_transforms.py
trojai/datagen/config.py
trojai/datagen/constants.py
trojai/datagen/datatype_xforms.py
trojai/datagen/entity.py
trojai/datagen/experiment.py
trojai/datagen/file_trigger.py
trojai/datagen/image_affine_xforms.py
trojai/datagen/image_brightness_xforms.py
trojai/datagen/image_conversion_utils.py
trojai/datagen/image_entity.py
trojai/datagen/image_insert_utils.py
trojai/datagen/image_size_xforms.py
trojai/datagen/image_triggers.py
trojai/datagen/insert_merges.py
trojai/datagen/instagram_xforms.py
trojai/datagen/label_behavior.py
trojai/datagen/lighting_utils.py
trojai/datagen/merge_interface.py
trojai/datagen/noise_xforms.py
trojai/datagen/pipeline.py
trojai/datagen/polygon_trigger.py
trojai/datagen/random_color_xforms.py
trojai/datagen/static_color_xforms.py
trojai/datagen/text_entity.py
trojai/datagen/text_replacement_xforms.py
trojai/datagen/transform_interface.py
trojai/datagen/utils.py
trojai/datagen/xform_merge_pipeline.py
trojai/modelgen/__init__.py
trojai/modelgen/adversarial_fbf_optimizer.py
trojai/modelgen/adversarial_pgd_optimizer.py
trojai/modelgen/architecture_factory.py
trojai/modelgen/config.py
trojai/modelgen/conlleval.py
trojai/modelgen/constants.py
trojai/modelgen/data_configuration.py
trojai/modelgen/data_descriptions.py
trojai/modelgen/data_manager.py
trojai/modelgen/datasets.py
trojai/modelgen/default_optimizer.py
trojai/modelgen/model_generator.py
trojai/modelgen/model_generator_interface.py
trojai/modelgen/ner_torchtext_optimizer.py
trojai/modelgen/optimizer_interface.py
trojai/modelgen/runner.py
trojai/modelgen/torchtext_optimizer.py
trojai/modelgen/torchtext_pgd_optimizer_fixed_embedding.py
trojai/modelgen/training_statistics.py
trojai/modelgen/uge_model_generator.py
trojai/modelgen/utils.py
trojai/modelgen/architectures/__init__.py
trojai-0.2.23.dist-info/LICENSE
trojai-0.2.23.dist-info/METADATA
trojai-0.2.23.dist-info/WHEEL
trojai-0.2.23.dist-info/dependency_links.txt
trojai-0.2.23.dist-info/top_level.txt
trojai-0.2.23.dist-info/RECORD
