Metadata-Version: 2.1
Name: trojai
Version: 0.2.23
Summary: TrojAI model and dataset generation library
Home-page: https://github.com/trojai/trojai
Author: Kiran Karra, Chace Ashcraft, Nat Kavaler, Michael Majurski, Taylor Kulp-McDowall
Author-email: kiran.karra@jhuapl.edu,chace.ashcraft@jhuapl.edu,nathaniel.kavaler@jhaupl.edu,michael.majurski@nist.gov,taylor.kulp-mcdowall@iarpa.gov
License: Apache License 2.0
Keywords: deep-learning trojan adversarial
Platform: UNKNOWN
Classifier: Development Status :: 3 - Alpha
Classifier: Intended Audience :: Developers
Classifier: Intended Audience :: Science/Research
Classifier: Topic :: Scientific/Engineering
Classifier: Topic :: Scientific/Engineering :: Artificial Intelligence
Classifier: License :: OSI Approved :: Apache Software License
Classifier: Programming Language :: Python :: 3 :: Only
Requires-Python: >=3
Requires-Dist: numpy (>=1.19.2)
Requires-Dist: pandas (>=1.0.3)
Requires-Dist: scikit-image (>=0.17.2)
Requires-Dist: joblib (>=0.14.1)
Requires-Dist: scipy (>=1.5.3)
Requires-Dist: pillow (>=7.1.2)
Requires-Dist: scikit-learn (>=0.23.0)
Requires-Dist: tqdm (>=4.46.0)
Requires-Dist: opencv-python (>=4.2.0.34)
Requires-Dist: torch (==1.7.0)
Requires-Dist: torchvision (==0.8.0)
Requires-Dist: torchtext (==0.8.0)
Requires-Dist: blend-modes
Requires-Dist: spacy (>=2.2.0)
Requires-Dist: cloudpickle (>=1.4.1)
Requires-Dist: Wand (>=0.5.9)
Requires-Dist: nltk (>=3.5)
Requires-Dist: pyllist (>=0.3)
Requires-Dist: albumentations
Requires-Dist: advertorch
Requires-Dist: nltk
Requires-Dist: pyllist
Requires-Dist: transformers (==4.5.1)
Requires-Dist: kaggle
Requires-Dist: tb-nightly
Requires-Dist: future
Provides-Extra: test
Requires-Dist: nose (==1.3.7) ; extra == 'test'
Requires-Dist: coverage (==5.0.3) ; extra == 'test'
Requires-Dist: mock ; extra == 'test'
